apiqa_storage/__init__.py
apiqa_storage/admin.py
apiqa_storage/files.py
apiqa_storage/managers.py
apiqa_storage/minio_storage.py
apiqa_storage/models.py
apiqa_storage/routers.py
apiqa_storage/serializers.py
apiqa_storage/settings.py
apiqa_storage/staff_urls.py
apiqa_storage/tasks.py
apiqa_storage/urls.py
apiqa_storage/validators.py
apiqa_storage/views.py
apiqa_storage/viewsets.py
apiqa_storage/http/__init__.py
apiqa_storage/http/range.py
apiqa_storage/http/response.py
apiqa_storage/migrations/0001_initial.py
apiqa_storage/migrations/0002_auto_20190801_1236.py
apiqa_storage/migrations/0003_auto_20191017_1105.py
apiqa_storage/migrations/0004_attachment_tags.py
apiqa_storage/migrations/0005_auto_20200522_0609.py
apiqa_storage/migrations/0006_auto_20200522_0624.py
apiqa_storage/migrations/0007_auto_20200803_1004.py
apiqa_storage/migrations/0008_attachment_linked_from.py
apiqa_storage/migrations/__init__.py
apiqa_storage-2.10.0.dist-info/LICENSE
apiqa_storage-2.10.0.dist-info/METADATA
apiqa_storage-2.10.0.dist-info/WHEEL
apiqa_storage-2.10.0.dist-info/top_level.txt
apiqa_storage-2.10.0.dist-info/RECORD
