Metadata-Version: 2.1
Name: apiqa-storage
Version: 2.10.0
Summary: Apiqa user storage backend for django projects
Home-page: https://github.com/pik-software/apiqa-storage.git
Author: pik-software
Author-email: no-reply@pik-software.ru
License: UNKNOWN
Project-URL: Bug Reports, https://gitlab.pik-software.ru/apiqa/apiqa-storage/issues
Project-URL: Funding, https://gitlab.pik-software.ru/apiqa/apiqa-storage
Project-URL: Say Thanks!, https://saythanks.io/to/pik_software
Project-URL: Source, https://gitlab.pik-software.ru/apiqa/apiqa-storage
Keywords: apiqa django
Platform: UNKNOWN
Classifier: Development Status :: 5 - Production/Stable
Classifier: Intended Audience :: Developers
Classifier: Topic :: Software Development
Classifier: License :: OSI Approved :: MIT License
Classifier: Programming Language :: Python :: 3.6
Classifier: Programming Language :: Python :: 3.7
Classifier: Programming Language :: Python :: 3.8
Requires-Python: ~=3.6
Requires-Dist: django (>=2.1)
Requires-Dist: djangorestframework (>=3.9)
Requires-Dist: humanfriendly (>=4.18)
Requires-Dist: python-slugify (>=1.2.6)
Requires-Dist: minio (==7.0.2)
Requires-Dist: celery
Provides-Extra: dev
Requires-Dist: responses (==0.13.1) ; extra == 'dev'
Requires-Dist: prospector (==1.2.0) ; extra == 'dev'
Requires-Dist: factory-boy ; extra == 'dev'
Requires-Dist: freezegun (==1.1.0) ; extra == 'dev'
Requires-Dist: pdbpp (==0.10.2) ; extra == 'dev'
Requires-Dist: pytest-xdist (==2.2.1) ; extra == 'dev'
Requires-Dist: pytest (==6.2.2) ; extra == 'dev'
Requires-Dist: pytest-cov (==2.11.1) ; extra == 'dev'
Requires-Dist: pytest-django (==4.1.0) ; extra == 'dev'
Requires-Dist: pytest-benchmark (==3.2.3) ; extra == 'dev'
Requires-Dist: pytest-mock (==3.5.1) ; extra == 'dev'
Requires-Dist: mypy (>=0.600) ; extra == 'dev'
Requires-Dist: psycopg2-binary (==2.8.6) ; extra == 'dev'
Requires-Dist: dj-database-url (==0.5.0) ; extra == 'dev'
Requires-Dist: twine (>=3.1.1) ; extra == 'dev'
